netcl/__init__.py
netcl/amp.py
netcl/autograd/__init__.py
netcl/autograd/debug.py
netcl/autograd/engine.py
netcl/autograd/ops.py
netcl/core/__init__.py
netcl/core/backend.py
netcl/core/capabilities.py
netcl/core/device.py
netcl/core/device_profile.py
netcl/core/kernel_selector.py
netcl/core/memory.py
netcl/core/parameter.py
netcl/core/tensor.py
netcl/core/kernels/__init__.py
netcl/core/kernels/primitives.py
netcl/data/augment.py
netcl/data/augment_gpu.py
netcl/data/dataloader.py
netcl/data/filters.py
netcl/distributed/__init__.py
netcl/distributed/collectives.py
netcl/distributed/data_parallel.py
netcl/distributed/device_manager.py
netcl/distributed/trainer.py
netcl/io/__init__.py
netcl/io/checkpoint.py
netcl/io/serialization.py
netcl/nn/__init__.py
netcl/nn/batchnorm.py
netcl/nn/decorators.py
netcl/nn/factory.py
netcl/nn/functional.py
netcl/nn/groupnorm.py
netcl/nn/init.py
netcl/nn/layernorm.py
netcl/nn/layers.py
netcl/nn/loss.py
netcl/nn/modules.py
netcl/nn/padding.py
netcl/nn/pooling.py
netcl/nn/residual.py
netcl/nn/resnet.py
netcl/nn/simple.py
netcl/ops/__init__.py
netcl/ops/broadcast.py
netcl/ops/conv2d.py
netcl/ops/conv2d_cpu.py
netcl/ops/conv2d_optimized.py
netcl/ops/conv_transpose2d.py
netcl/ops/depthwise_conv2d.py
netcl/ops/elementwise.py
netcl/ops/elementwise_optimized.py
netcl/ops/fused_ops.py
netcl/ops/im2col.py
netcl/ops/matmul.py
netcl/ops/matmul_optimized.py
netcl/ops/reduction.py
netcl/ops/softmax.py
netcl/ops/softmax_fp16.py
netcl/ops/transpose.py
netcl/optim/__init__.py
netcl/optim/adam.py
netcl/optim/adamw.py
netcl/optim/amp.py
netcl/optim/clip.py
netcl/optim/lr_plateau.py
netcl/optim/lr_scheduler.py
netcl/optim/momentum.py
netcl/optim/rmsprop.py
netcl/optim/sgd.py
netcl/profiling/__init__.py
netcl/profiling/autotuner.py
netcl/profiling/timing.py
netcl/runtime/__init__.py
netcl/runtime/graph.py
netcl/runtime/graph_fusion.py
netcl/runtime/scheduler.py
netcl/trainer/__init__.py
netcl/trainer/trainer.py
netcl/utils/__init__.py
netcl/utils/data.py
netcl-0.1.3.dist-info/licenses/LICENSE
netcl-0.1.3.dist-info/METADATA
netcl-0.1.3.dist-info/WHEEL
netcl-0.1.3.dist-info/top_level.txt
netcl-0.1.3.dist-info/RECORD
