Metadata-Version: 2.4
Name: netcl
Version: 0.1.3
Summary: PyOpenCL-based deep learning playground with autograd, kernels, and high-level APIs.
Author: netcl contributors
License-Expression: MIT
Project-URL: Repository, https://bbwebservice.online/lukas/netcl
Keywords: opencl,deep-learning,autograd,gpu
Classifier: Programming Language :: Python :: 3
Classifier: Operating System :: OS Independent
Requires-Python: >=3.10
License-File: LICENSE
Requires-Dist: numpy>=1.22
Requires-Dist: pyopencl>=2022.3
Dynamic: license-file
